click_option_group/__init__.py
click_option_group/_core.py
click_option_group/_decorators.py
click_option_group/_helpers.py
click_option_group/_version.py
click_option_group/py.typed
click_option_group-0.5.6.dist-info/LICENSE
click_option_group-0.5.6.dist-info/METADATA
click_option_group-0.5.6.dist-info/WHEEL
click_option_group-0.5.6.dist-info/top_level.txt
click_option_group-0.5.6.dist-info/RECORD
