Metadata-Version: 2.1
Name: click-option-group
Version: 0.5.6
Summary: Option groups missing in Click
Home-page: https://github.com/click-contrib/click-option-group
Author: Eugene Prilepin
Author-email: esp.home@gmail.com
License: BSD-3-Clause
Project-URL: Code, https://github.com/click-contrib/click-option-group
Project-URL: Issue tracker, https://github.com/click-contrib/click-option-group/issues
Project-URL: Documentation, https://click-option-group.readthedocs.io
Classifier: Development Status :: 4 - Beta
Classifier: Intended Audience :: Developers
Classifier: Environment :: Console
Classifier: Topic :: Software Development :: Libraries
Classifier: License :: OSI Approved :: BSD License
Classifier: Operating System :: OS Independent
Classifier: Programming Language :: Python
Classifier: Programming Language :: Python :: 3 :: Only
Classifier: Programming Language :: Python :: 3
Classifier: Programming Language :: Python :: 3.6
Classifier: Programming Language :: Python :: 3.7
Classifier: Programming Language :: Python :: 3.8
Classifier: Programming Language :: Python :: 3.9
Classifier: Programming Language :: Python :: 3.10
Classifier: Programming Language :: Python :: 3.11
Requires-Python: >=3.6,<4
Provides-Extra: docs
Provides-Extra: tests
Provides-Extra: tests_cov
License-File: LICENSE
